pcm_spaghetti-1.2.dist-info/licenses/LICENSE
spaghetti/__init__.py
spaghetti/_spaghetti_modules.py
spaghetti/cli_inference.py
spaghetti/dataset.py
spaghetti/inferences.py
spaghetti/train.py
spaghetti/utils.py
pcm_spaghetti-1.2.dist-info/METADATA
pcm_spaghetti-1.2.dist-info/WHEEL
pcm_spaghetti-1.2.dist-info/entry_points.txt
pcm_spaghetti-1.2.dist-info/top_level.txt
pcm_spaghetti-1.2.dist-info/RECORD
