Metadata-Version: 2.4
Name: pcm-spaghetti
Version: 1.2
Summary: A PyTorch implementation of the SPAGHETTI model for phase-contrast microscopy image transformation
Home-page: https://github.com/schwartzlab-methods/spaghetti
Author: Richard (Zhi Fei) Dong, Chris McIntosh, Gregory W. Schwartz
Author-email: gregory.schwartz@uhn.ca
Classifier: Programming Language :: Python :: 3
Classifier: License :: OSI Approved :: GNU General Public License v3 (GPLv3)
Classifier: Operating System :: OS Independent
Requires-Python: >=3.9
License-File: LICENSE
Requires-Dist: torch>=2.2.0
Requires-Dist: torchvision>=0.17.0
Requires-Dist: numpy>=1.26.4
Requires-Dist: Pillow>=10.3.0
Requires-Dist: scikit-image>=0.18.3
Requires-Dist: pytorch-lightning>=2.3.3
Requires-Dist: tqdm>=4.66.4
Dynamic: author
Dynamic: author-email
Dynamic: classifier
Dynamic: description
Dynamic: description-content-type
Dynamic: home-page
Dynamic: license-file
Dynamic: requires-dist
Dynamic: requires-python
Dynamic: summary
